utilstools/__init__.py
utilstools/utilstools.py
utilstools-1.0.0.dist-info/licenses/LICENSE
utilstools-1.0.0.dist-info/METADATA
utilstools-1.0.0.dist-info/WHEEL
utilstools-1.0.0.dist-info/top_level.txt
utilstools-1.0.0.dist-info/RECORD
