Metadata-Version: 2.4
Name: utilstools
Version: 1.0.0
Summary: A package for usefull tools.
Home-page: 
Author: Nickels
Author-email: Nickels74130@outlook.fr
Classifier: Programming Language :: Python :: 3
Classifier: License :: Other/Proprietary License
Classifier: Operating System :: OS Independent
License-File: LICENSE
Dynamic: author
Dynamic: author-email
Dynamic: classifier
Dynamic: description
Dynamic: description-content-type
Dynamic: license-file
Dynamic: summary
